apiscan/__init__.py
apiscan/cli.py
apiscan/config.py
apiscan/discovery.py
apiscan/http.py
apiscan/models.py
apiscan/scanner.py
apiscan/checks/__init__.py
apiscan/checks/auth.py
apiscan/checks/cors.py
apiscan/checks/headers.py
apiscan/checks/info_leak.py
apiscan/checks/input_validation.py
apiscan/checks/rate_limit.py
apiscan/checks/tls.py
apiscan/report/__init__.py
apiscan/report/html_report.py
apiscan/report/json_report.py
apiscan/templates/report.html.j2
apiscan-0.1.1.dist-info/licenses/LICENSE
apiscan-0.1.1.dist-info/METADATA
apiscan-0.1.1.dist-info/WHEEL
apiscan-0.1.1.dist-info/entry_points.txt
apiscan-0.1.1.dist-info/top_level.txt
apiscan-0.1.1.dist-info/RECORD
