Metadata-Version: 2.4
Name: apiscan
Version: 0.1.1
Summary: A safe, public-API security scanner CLI
Author: Samuel Selasi
License: MIT
Requires-Python: >=3.10
License-File: LICENSE
Requires-Dist: httpx>=0.26
Requires-Dist: rich>=13.0
Requires-Dist: pydantic>=2.0
Requires-Dist: jinja2>=3.1
Provides-Extra: dev
Requires-Dist: pytest>=7.0; extra == "dev"
Requires-Dist: pytest-asyncio>=0.23; extra == "dev"
Requires-Dist: pytest-cov>=4.0; extra == "dev"
Dynamic: license-file
